pshlex/__init__.py
pshlex/py.typed
pshlex-0.1.1.dist-info/METADATA
pshlex-0.1.1.dist-info/WHEEL
pshlex-0.1.1.dist-info/licenses/LICENSES/BSD-2-Clause.txt
pshlex-0.1.1.dist-info/RECORD
