Metadata-Version: 2.4
Name: pshlex
Version: 0.1.1
Summary: Join various stringifiable objects and quote them for the shell
Project-URL: Homepage, https://devel.ringlet.net/textproc/pshlex/
Project-URL: Changes, https://devel.ringlet.net/textproc/pshlex/changes/
Project-URL: Issue Tracker, https://gitlab.com/ppentchev/pshlex/-/issues
Project-URL: Source Code, https://gitlab.com/ppentchev/pshlex
Author-email: Peter Pentchev <roam@ringlet.net>
License-Expression: BSD-2-Clause
License-File: LICENSES/BSD-2-Clause.txt
Classifier: Development Status :: 5 - Production/Stable
Classifier: Intended Audience :: Developers
Classifier: Operating System :: OS Independent
Classifier: Programming Language :: Python
Classifier: Programming Language :: Python :: 3
Classifier: Programming Language :: Python :: 3 :: Only
Classifier: Programming Language :: Python :: 3.8
Classifier: Programming Language :: Python :: 3.9
Classifier: Programming Language :: Python :: 3.10
Classifier: Programming Language :: Python :: 3.11
Classifier: Programming Language :: Python :: 3.12
Classifier: Programming Language :: Python :: 3.13
Classifier: Programming Language :: Python :: 3.14
Classifier: Topic :: Software Development :: Libraries
Classifier: Topic :: Software Development :: Libraries :: Python Modules
Classifier: Typing :: Typed
Requires-Python: >=3.8
